pycxx/__init__.py
pycxx-0.0.4.dist-info/METADATA
pycxx-0.0.4.dist-info/WHEEL
pycxx-0.0.4.dist-info/top_level.txt
pycxx-0.0.4.dist-info/RECORD
