Metadata-Version: 2.1
Name: pycxx
Version: 0.0.4
Summary: simple crypting library ;)
Home-page: https://rubbiekelvin@bitbucket.org/rubbiekelvin/cxx
Author: Rubbie Kelvin Voltsman
Author-email: rubbiekelvinvoltsman@gmail.com
License: MIT
Platform: UNKNOWN
Classifier: Programming Language :: Python :: 3
Classifier: License :: OSI Approved :: MIT License
Classifier: Operating System :: OS Independent
Requires-Python: >=3.0
